mem0rylol/__init__.py
mem0rylol/base/__init__.py
mem0rylol/base/embeddings.py
mem0rylol/base/llms.py
mem0rylol/base/vector_stores.py
mem0rylol/config.py
mem0rylol/embeddings/__init__.py
mem0rylol/embeddings/google_genai.py
mem0rylol/llms/__init__.py
mem0rylol/llms/cerebras.py
mem0rylol/memory/__init__.py
mem0rylol/memory/memory_manager.py
mem0rylol/memory/memory_types.py
mem0rylol/schemas/__init__.py
mem0rylol/schemas/base.py
mem0rylol/schemas/lancedb.py
mem0rylol/utils.py
mem0rylol/vector_stores/__init__.py
mem0rylol/vector_stores/lancedb.py
mem0rylol-0.2.1.dist-info/LICENSE.txt
mem0rylol-0.2.1.dist-info/METADATA
mem0rylol-0.2.1.dist-info/WHEEL
mem0rylol-0.2.1.dist-info/RECORD
