Metadata-Version: 2.1
Name: mem0rylol
Version: 0.2.1
Summary: A sophisticated AI memory layer.
License: GNU
Author: toeknee
Requires-Python: >=3.11,<4.0
Classifier: License :: Other/Proprietary License
Classifier: Programming Language :: Python :: 3
Classifier: Programming Language :: Python :: 3.11
Classifier: Programming Language :: Python :: 3.12
Requires-Dist: dynaconf (>=3.2.0,<4.0.0)
Requires-Dist: google-generativeai (>=0.7.0,<0.8.0)
Requires-Dist: lancedb (>=0.3.0,<0.4.0)
Requires-Dist: langchain (>=0.2.16,<0.3.0)
Requires-Dist: langchain-cerebras (>=0.1.0,<0.2.0)
Requires-Dist: langchain-community (>=0.2.16,<0.3.0)
Requires-Dist: langchain-core (>=0.2.39,<0.3.0)
Requires-Dist: langchain-google-genai (==1.0.10)
Requires-Dist: packaging (>=23.2,<24.0)
Requires-Dist: pydantic (>=2.0,<3.0)
